percemon.abi3.so
lib/libPerceMon.a
percemon/__init__.pyi
percemon/py.typed
percemon-1.0.3.dist-info/METADATA
percemon-1.0.3.dist-info/WHEEL
percemon-1.0.3.dist-info/RECORD
percemon-1.0.3.dist-info/licenses/LICENSE
