Metadata-Version: 2.1
Name: percemon
Version: 1.0.3
Author-Email: Anand Balakrishnan <anandbala1597@gmail.com>
Requires-Python: >=3.10
